rustmaps/__init__.py
rustmaps/cli.py
rustmaps-0.1.0.dist-info/LICENSE
rustmaps-0.1.0.dist-info/METADATA
rustmaps-0.1.0.dist-info/WHEEL
rustmaps-0.1.0.dist-info/entry_points.txt
rustmaps-0.1.0.dist-info/top_level.txt
rustmaps-0.1.0.dist-info/RECORD
