Metadata-Version: 2.2
Name: rustmaps
Version: 0.1.0
Summary: Rustmaps Generator: A library and CLI tool for generating maps.
Author-email: mainloot <github@mainloot.com>
License: MIT
Project-URL: Source, https://github.com/maintc/rustmaps-generator
Classifier: Programming Language :: Python :: 3
Classifier: License :: OSI Approved :: MIT License
Classifier: Operating System :: OS Independent
Requires-Python: >=3.7
License-File: LICENSE
Requires-Dist: click>=8.1.8
Requires-Dist: platformdirs>=4.3.6
Requires-Dist: pydantic>=2.10.5
Requires-Dist: Requests>=2.32.3
Provides-Extra: dev
Requires-Dist: pytest>=8.3.4; extra == "dev"
Requires-Dist: pytest-cov>=6.0.0; extra == "dev"
Requires-Dist: black>=24.10.0; extra == "dev"
